cachestore/__init__.py
cachestore/__main__.py
cachestore/cache.py
cachestore/commands/__init__.py
cachestore/commands/list.py
cachestore/commands/prune.py
cachestore/commands/remove.py
cachestore/commands/subcommand.py
cachestore/common/__init__.py
cachestore/common/astnorm.py
cachestore/common/filelock.py
cachestore/common/selector.py
cachestore/common/table.py
cachestore/config.py
cachestore/formatters/__init__.py
cachestore/formatters/formatter.py
cachestore/formatters/pickle_formatter.py
cachestore/hashers/__init__.py
cachestore/hashers/hasher.py
cachestore/hashers/pickle_hasher.py
cachestore/metadata.py
cachestore/py.typed
cachestore/storages/__init__.py
cachestore/storages/local_storage.py
cachestore/storages/storage.py
cachestore/util.py
cachestore-0.4.0.dist-info/LICENSE
cachestore-0.4.0.dist-info/METADATA
cachestore-0.4.0.dist-info/WHEEL
cachestore-0.4.0.dist-info/entry_points.txt
cachestore-0.4.0.dist-info/RECORD
