Metadata-Version: 2.3
Name: cachestore
Version: 0.4.0
Summary: Function Cache Management Tool for Python
License: MIT
Keywords: python,cache
Author: altescy
Author-email: me@altescy.jp
Requires-Python: >=3.8,<4.0
Classifier: License :: OSI Approved :: MIT License
Classifier: Programming Language :: Python :: 3
Classifier: Programming Language :: Python :: 3.8
Classifier: Programming Language :: Python :: 3.9
Classifier: Programming Language :: Python :: 3.10
Classifier: Programming Language :: Python :: 3.11
Classifier: Programming Language :: Python :: 3.12
Classifier: Programming Language :: Python :: 3.13
Project-URL: Homepage, https://github.com/altescy/cachestore
